[{"num_versions": 6, "url_citation": null, "title": "Delivery of a urology online course using moodle versus didactic lectures methods", "url": "http://www.sciencedirect.com/science/article/pii/S1386505614002160", "url_versions": "http://scholar.google.com/scholar?cluster=5260714283680965775&hl=en&as_sdt=1,5&sciodt=1,5&as_vis=1", "authors": "LO Reis, O Ikari, KA Taha-Neto, A Gugliotta\u2026 - International journal of  \u2026", "excerpt": "Purpose To subjectively and objectively compare an accessible interactive electronic library using Moodle with lectures for urology teaching of medical students. Methods Forty consecutive fourth-year medical students and one urology teacher were exposed to two  ...", "url_pdf": null, "num_citations": 0, "cluster_id": null, "year": "2015", "url_citations": null}]