[{"num_versions": 0, "url_citation": null, "title": "Students as change agents in a town-wide sustainability transformation: the Oberlin Project at Oberlin College", "url": "http://www.sciencedirect.com/science/article/pii/S187734351500069X", "url_versions": null, "authors": "DR Daneri, G Trencher, J Petersen - Current Opinion in Environmental  \u2026", "excerpt": "An increasing number of colleges and universities are playing a crucial role in driving societal transformations and creating the physical and social conditions for accelerating progress towards sustainability. The potential of multi-stakeholder partnerships to enrich  ...", "url_pdf": null, "num_citations": 0, "cluster_id": null, "year": "2015", "url_citations": null}, {"num_versions": 0, "url_citation": null, "title": "Embedding sustainability learning pathways across the university", "url": "http://www.sciencedirect.com/science/article/pii/S1877343515000767", "url_versions": null, "authors": "J Marcus, NC Coops, S Ellis, J Robinson - Current Opinion in  \u2026", "excerpt": "The University of British Columbia's (UBC) long-term vision is to embed sustainability in all of its undergraduate teaching programs. The University has described four student sustainability attributes\u2014Holistic Systems Thinking, Sustainability Knowledge, Awareness  ...", "url_pdf": null, "num_citations": 1, "cluster_id": "16764183435752770560", "year": "2015", "url_citations": "http://scholar.google.com/scholar?cites=16764183435752770560&as_sdt=2005&sciodt=1,5&hl=en"}]